ds_uv_test_package/__init__.py
ds_uv_test_package/operations.py
ds_uv_test_package-0.0.2.dist-info/METADATA
ds_uv_test_package-0.0.2.dist-info/WHEEL
ds_uv_test_package-0.0.2.dist-info/entry_points.txt
ds_uv_test_package-0.0.2.dist-info/RECORD
