Metadata-Version: 2.4
Name: ds-uv-test-package
Version: 0.0.2
Summary: testr nuh
Author-email: Dmitry Drozdov <ds.drozdov@gmail.com>
Requires-Python: >=3.13
